[
{"id":1,"priority":1,"action":{"type":"block"},"condition":{"regexFilter":"(?i)/(adframe|ad-frame|adserver|ad-server|adservice|adsystem|adbanner|ad-banner|ad_banner|advertising|advertisement)/","resourceTypes":["script","image","sub_frame","xmlhttprequest","media","object","ping","websocket","other"]}},
{"id":2,"priority":1,"action":{"type":"block"},"condition":{"regexFilter":"(?i)/(popunder|pop-under|pop_under|popmedia|clickunder|click-under|popad|pop-ad)/","resourceTypes":["script","image","sub_frame","xmlhttprequest","media","object","ping","websocket","other"]}},
{"id":3,"priority":1,"action":{"type":"block"},"condition":{"regexFilter":"(?i)[?&](adslot|ad_slot|adunit|ad_unit|adzone|ad_zone|adsize|ad_size|adtype|ad_type)=","resourceTypes":["script","image","sub_frame","xmlhttprequest","media","object","ping","other"]}},
{"id":4,"priority":1,"action":{"type":"block"},"condition":{"regexFilter":"(?i)/(www/)?delivery/[a-z]{2,7}\\.(php|js)","resourceTypes":["script","image","sub_frame","xmlhttprequest","other"]}},
{"id":5,"priority":1,"action":{"type":"block"},"condition":{"regexFilter":"(?i)/(openx|revive-adserver|adserver)/","resourceTypes":["script","image","sub_frame","xmlhttprequest","media","object","other"]}},
{"id":6,"priority":1,"action":{"type":"block"},"condition":{"regexFilter":"(?i)/(banner_view|bannerview|show_?ads?|get_?ads?|serve_?ads?|deliver_?ads?)\\b","resourceTypes":["script","image","sub_frame","xmlhttprequest","other"]}},
{"id":7,"priority":1,"action":{"type":"block"},"condition":{"regexFilter":"(?i)[?&](zoneid|bannerid|campaignid|adcampaign|advertiserid)=","resourceTypes":["script","image","sub_frame","xmlhttprequest","other"]}},
{"id":8,"priority":1,"action":{"type":"block"},"condition":{"regexFilter":"(?i)/(adsbygoogle|prebid|prebid\\.min|pubads|gpt|gpt\\.min)\\.js","resourceTypes":["script"]}}
]
